Metadata-Version: 1.1
Name: hammock-rest
Version: 0.0.1
Summary: A good place to REST
Home-page: http://github.com/stratoscale/hammock.git
Author: Eyal Posener
Author-email: eyal@stratoscale.com
License: Apache License 2.0
Keywords: REST
Platform: UNKNOWN
Classifier: Development Status :: 4 - Beta
Classifier: Intended Audience :: Developers
Classifier: License :: OSI Approved :: Apache Software License
Classifier: Natural Language :: English
Classifier: Operating System :: POSIX :: Linux
Classifier: Programming Language :: Python :: 2.7
Classifier: Topic :: Internet :: WWW/HTTP :: WSGI :: Middleware
